fons/__init__.py
fons/aio.py
fons/all.py
fons/argv.py
fons/crypto.py
fons/debug.py
fons/dict_ops.py
fons/errors.py
fons/event.py
fons/fsync.py
fons/func.py
fons/gui.py
fons/host.py
fons/io.py
fons/iter.py
fons/log.py
fons/log311.py
fons/log35.py
fons/log38.py
fons/nan.py
fons/os.py
fons/processes.py
fons/py.py
fons/pyops.py
fons/reg.py
fons/sched.py
fons/threads.py
fons/time.py
fons/verify.py
fons/verify_old.py
fons/dtype/__init__.py
fons/dtype/dtype.py
fons/dtype/merging.py
fons/dtype/store.py
fons/math/__init__.py
fons/math/graph.py
fons/math/round.py
fons/math/series.py
fons/net/__init__.py
fons/net/url.py
fons/net/urlstr.py
fons-0.4.0.dist-info/METADATA
fons-0.4.0.dist-info/WHEEL
fons-0.4.0.dist-info/top_level.txt
fons-0.4.0.dist-info/RECORD
