Metadata-Version: 2.1
Name: fons
Version: 0.4.0
Summary: A broad range of python tools. Some uses: round datetimes, verify input data, execute functions by schedule, parse argv
Home-page: https://github.com/binares/fons
Author: binares
Author-email: binares@protonmail.com
License: MIT
Requires-Python: >=3.5
Requires-Dist: aiohttp >=2.0
Requires-Dist: aiohttp-socks >=0.2
Requires-Dist: requests >=2.0
Requires-Dist: cryptography >=1.8
Requires-Dist: filelock >=3.0
Requires-Dist: ntplib >=0.3.3
Requires-Dist: pandas >=0.21
Requires-Dist: PyYAML >=3.10
